QTFITIT_example_Fephen3/Fephen3_Energy.txt
QTFITIT_example_Fephen3/Fephen3_bond_3ligand.txt
QTFITIT_example_Fephen3/Fephen3_xmu.txt
QTFITIT_example_Fephen3/Readme.txt
QTFITIT_example_Fephen3/__init__.py
QTFITIT_example_Fephen3/exp_excited.txt
QTFITIT_example_Fephen3/input.txt
QTFITIT_example_Fephen3/input_Fephen3.txt
QTFITIT_example_Fephen3/input_Fephen3_from_parent_directory.txt
QTFITIT_example_IHS500/IHS_500_energy.txt
QTFITIT_example_IHS500/IHS_500_mu_conv.txt
QTFITIT_example_IHS500/IHS_500_params.txt
QTFITIT_example_IHS500/Readme.txt
QTFITIT_example_IHS500/__init__.py
QTFITIT_example_IHS500/exp_excited.txt
QTFITIT_example_IHS500/input.txt
QTFITIT_example_IHS500/input_IHS500.txt
QTFITIT_example_IHS500/input_IHS500_from_parent_directory.txt
QTFITIT_example_IHS729/IHS_729_energy.txt
QTFITIT_example_IHS729/IHS_729_mu_conv.txt
QTFITIT_example_IHS729/IHS_729_params.txt
QTFITIT_example_IHS729/Readme.txt
QTFITIT_example_IHS729/__init__.py
QTFITIT_example_IHS729/exp_excited.txt
QTFITIT_example_IHS729/input.txt
QTFITIT_example_IHS729/input_IHS729.txt
QTFITIT_example_IHS729/input_IHS729_from_parent_directory.txt
src/QTFITIT_pip_test.py
src/__init__.py
QTFITIT-0.1.dist-info/METADATA
QTFITIT-0.1.dist-info/WHEEL
QTFITIT-0.1.dist-info/entry_points.txt
QTFITIT-0.1.dist-info/top_level.txt
QTFITIT-0.1.dist-info/RECORD
